nanogcg_redteam/__init__.py
nanogcg_redteam/gcg.py
nanogcg_redteam/target.py
nanogcg_redteam/utils.py
nanogcg_redteam-0.1.2.dist-info/licenses/LICENSE
nanogcg_redteam-0.1.2.dist-info/METADATA
nanogcg_redteam-0.1.2.dist-info/WHEEL
nanogcg_redteam-0.1.2.dist-info/top_level.txt
nanogcg_redteam-0.1.2.dist-info/RECORD
