Metadata-Version: 2.4
Name: nanogcg-redteam
Version: 0.1.2
Summary: An adaptation of nanoGCG more suitable for GenAI Red Teaming exercises against deployed systems.
Author-email: Felipe Campos Penha <felipe.penha@owasp.org>
Maintainer-email: Felipe Campos Penha <felipe.penha@owasp.org>
Project-URL: Homepage, https://github.com/felipepenha/nanoGCG-redteam
Project-URL: Issues, https://github.com/felipepenha/nanoGCG-redteam/issues
Classifier: Programming Language :: Python :: 3
Classifier: License :: OSI Approved :: MIT License
Classifier: Operating System :: OS Independent
Requires-Python: >=3.9
License-File: LICENSE
Requires-Dist: protobuf
Requires-Dist: scipy>=1.7.0
Requires-Dist: sentencepiece>=0.2.0
Requires-Dist: torch>=2.0
Requires-Dist: transformers<=4.47.1,>=4.4
Dynamic: license-file
